{
  "kind": "collectionType",
  "collectionName": "documents",
  "info": {
    "name": "document",
    "description": ""
  },
  "options": {
    "increments": true,
    "timestamps": true,
    "draftAndPublish": true
  },
  "pluginOptions": {},
  "attributes": {
    "title": {
      "type": "string"
    },
    "slug": {
      "type": "uid",
      "targetField": "title"
    },
    "pdf": {
      "model": "file",
      "via": "related",
      "allowedTypes": [
        "files"
      ],
      "plugin": "upload",
      "required": false,
      "pluginOptions": {}
    },
    "document_subcategory": {
      "via": "documents",
      "model": "document-subcategories"
    },
    "text": {
      "type": "richtext"
    },
    "complicatedTable": {
      "type": "boolean"
    }
  }
}
